mediaflask/__init__.py
mediaflask/__main__.py
mediaflask/audiofile.py
mediaflask/web.py
mediaflask-0.2.1.dist-info/DESCRIPTION.rst
mediaflask-0.2.1.dist-info/entry_points.txt
mediaflask-0.2.1.dist-info/METADATA
mediaflask-0.2.1.dist-info/metadata.json
mediaflask-0.2.1.dist-info/RECORD
mediaflask-0.2.1.dist-info/top_level.txt
mediaflask-0.2.1.dist-info/WHEEL
