Metadata-Version: 2.0
Name: mediaflask
Version: 0.2.1
Summary: Download audio from online videos.
Home-page: https://github.com/marcwebbie/mediaflask
Author: Marc Webbie
Author-email: marcwebbie@gmail.com
License: License :: OSI Approved :: MIT License
Download-URL: https://pypi.python.org/pypi/mediaflask
Platform: UNKNOWN
Classifier: Development Status :: 2 - Pre-Alpha
Classifier: Environment :: Console
Classifier: Intended Audience :: End Users/Desktop
Classifier: Natural Language :: English
Classifier: Operating System :: OS Independent
Classifier: Topic :: Security :: Cryptography
Classifier: License :: OSI Approved :: MIT License
Classifier: Programming Language :: Python
Classifier: Programming Language :: Python :: 2.7
Classifier: Programming Language :: Python :: 3
Classifier: Programming Language :: Python :: 3.2
Classifier: Programming Language :: Python :: 3.3
Classifier: Programming Language :: Python :: 3.4
Classifier: Programming Language :: Python :: 3.4
Requires-Dist: flask
Requires-Dist: peewee
Requires-Dist: youtube-dl
Requires-Dist: pydub
Requires-Dist: requests (==2.6.0)
Requires-Dist: awesome-slugify (==1.6.2)
